yacloud/__init__.py
yacloud/cloudfile.py
yacloud-0.1.0.dist-info/LICENSE.txt
yacloud-0.1.0.dist-info/METADATA
yacloud-0.1.0.dist-info/WHEEL
yacloud-0.1.0.dist-info/top_level.txt
yacloud-0.1.0.dist-info/RECORD
