Metadata-Version: 2.1
Name: yacloud
Version: 0.1.0
Summary: A micro package for working with yandex cloud services
Author: Dima Frolenko
Author-email: orangefrol@gmail.com
License: LICENSE.txt
License-File: LICENSE.txt
